nanobuild/__init__.py
nanobuild/builder.py
nanobuild/commands.py
nanobuild/environment.py
nanobuild/main.py
nanobuild/target.py
nanobuild/utility.py
nanobuild-0.3.dist-info/LICENSE
nanobuild-0.3.dist-info/METADATA
nanobuild-0.3.dist-info/WHEEL
nanobuild-0.3.dist-info/top_level.txt
nanobuild-0.3.dist-info/RECORD
