Metadata-Version: 2.1
Name: nanobuild
Version: 0.3
Summary: A very simple and customizable build system made in Python that generates Ninja.
Home-page: https://github.com/chibicitiberiu/nanobuild
Author: Tiberiu Chibici
Author-email: chibicitiberiu@zoho.eu
Project-URL: Bug Tracker, https://github.com/chibicitiberiu/nanobuild/issues
Classifier: Programming Language :: Python :: 3
Classifier: License :: OSI Approved :: MIT License
Classifier: Operating System :: OS Independent
Requires-Python: >=3.9
License-File: LICENSE
Requires-Dist: ninja-syntax
